MANIFEST.in
README.md
RELEASING.md
setup.cfg
setup.py
tox.ini
pyclpa/__init__.py
pyclpa/base.py
pyclpa/cli.py
pyclpa/util.py
pyclpa/wordlist.py
pyclpa.egg-info/PKG-INFO
pyclpa.egg-info/SOURCES.txt
pyclpa.egg-info/dependency_links.txt
pyclpa.egg-info/entry_points.txt
pyclpa.egg-info/not-zip-safe
pyclpa.egg-info/requires.txt
pyclpa.egg-info/top_level.txt
pyclpa/data/alias.tsv
pyclpa/data/clpa.main.json.bak
pyclpa/data/clpa.tsv
pyclpa/data/explicit.tsv
pyclpa/data/normalized.tsv
pyclpa/data/patterns.tsv
pyclpa/tests/__init__.py
pyclpa/tests/test_base.py
pyclpa/tests/test_cli.py
pyclpa/tests/test_util.py
pyclpa/tests/test_wordlist.py
pyclpa/tests/util.py
pyclpa/tests/data/KSL.tsv