Metadata-Version: 1.0
Name: pyclpa
Version: 1.0.0
Summary: A python library to check phonetic transcriptions
Home-page: https://github.com/glottobank/cpa
Author: Johann-Mattis List
Author-email: mattis.list@lingpy.org
License: GPL
Platform: UNKNOWN
